neuralib/decoding/__init__.py
neuralib/decoding/position.py
neuralib/locomotion/__init__.py
neuralib/locomotion/epoch.py
neuralib/locomotion/position.py
neuralib/rastermap/__init__.py
neuralib/rastermap/core.py
neuralib/rastermap/plot.py
neuralib/rastermap/run.py
neuralib_metric-0.7.0.dist-info/licenses/LICENSE
neuralib_metric-0.7.0.dist-info/METADATA
neuralib_metric-0.7.0.dist-info/WHEEL
neuralib_metric-0.7.0.dist-info/top_level.txt
neuralib_metric-0.7.0.dist-info/RECORD
