Metadata-Version: 2.4
Name: neuralib-metric
Version: 0.7.0
Summary: Tools for analysis metrics and computational modeling
Author-email: Yu-Ting Wei <ytsimon2004@gmail.com>, Ta-Shun Su <antoniost29@gmail.com>
License: BSD-3-Clause
Project-URL: Homepage, https://github.com/ytsimon2004/neuralib2
Project-URL: Documentation, https://neuralib2.readthedocs.io/en/latest/index.html
Project-URL: Repository, https://github.com/ytsimon2004/neuralib2
Project-URL: Issues, https://github.com/ytsimon2004/neuralib2/issues
Keywords: Parser,Segmentation,Morphology
Classifier: Programming Language :: Python :: 3.11
Classifier: Programming Language :: Python :: 3.12
Classifier: License :: OSI Approved :: BSD License
Classifier: Natural Language :: English
Classifier: Operating System :: OS Independent
Classifier: Topic :: Scientific/Engineering
Classifier: Intended Audience :: Science/Research
Classifier: Typing :: Typed
Requires-Python: <3.13,>=3.11
License-File: LICENSE
Requires-Dist: neuralib-utils[all]>=0.7.0
Requires-Dist: numpy
Requires-Dist: numba
Provides-Extra: rastermap
Requires-Dist: rastermap; extra == "rastermap"
Provides-Extra: all
Requires-Dist: neuralib-metric[rastermap]; extra == "all"
Dynamic: license-file
